aigym/__init__.py
aigym/_version.py
aigym/agent.py
aigym/env.py
aigym/exceptions.py
aigym/pprint.py
aigym/prompts.py
aigym/spaces.py
aigym/types.py
aigym-0.0.2.dist-info/licenses/LICENSE
aigym-0.0.2.dist-info/METADATA
aigym-0.0.2.dist-info/WHEEL
aigym-0.0.2.dist-info/top_level.txt
aigym-0.0.2.dist-info/RECORD
