Metadata-Version: 2.4
Name: aigym
Version: 0.0.2
Summary: Reinforcement learning environments for fine-tuning language models for reasoning tasks.
Author-email: Niels Bantilan <niels.bantilan@gmail.com>
Project-URL: Homepage, https://github.com/cosmicbboy/aigym
Classifier: Intended Audience :: Science/Research
Classifier: Intended Audience :: Developers
Classifier: License :: Other/Proprietary License
Classifier: Programming Language :: Python :: 3.9
Classifier: Programming Language :: Python :: 3.10
Classifier: Programming Language :: Python :: 3.11
Classifier: Programming Language :: Python :: 3.12
Classifier: Topic :: Scientific/Engineering
Classifier: Topic :: Scientific/Engineering :: Artificial Intelligence
Classifier: Topic :: Software Development
Classifier: Topic :: Software Development :: Libraries
Classifier: Topic :: Software Development :: Libraries :: Python Modules
Requires-Python: >=3.9
License-File: LICENSE
Requires-Dist: beautifulsoup4
Requires-Dist: html2text
Requires-Dist: httpx
Requires-Dist: gymnasium
Requires-Dist: markdownify
Requires-Dist: pydantic
Requires-Dist: pygame
Requires-Dist: python-dotenv
Requires-Dist: rich
Requires-Dist: tiktoken
Provides-Extra: ollama
Requires-Dist: ollama; extra == "ollama"
Provides-Extra: openai
Requires-Dist: openai; extra == "openai"
Provides-Extra: google-genai
Requires-Dist: google-genai; extra == "google-genai"
Dynamic: license-file
